Commands/__init__.py
Commands/core.py
Commands/errors.py
python_commandmaker-0.0.4.dist-info/LICENSE
python_commandmaker-0.0.4.dist-info/METADATA
python_commandmaker-0.0.4.dist-info/WHEEL
python_commandmaker-0.0.4.dist-info/top_level.txt
python_commandmaker-0.0.4.dist-info/RECORD
