Metadata-Version: 2.1
Name: python-commandmaker
Version: 0.0.4
Summary: Python module for discord bot like commands from the console
Home-page: UNKNOWN
Author: Cube Riser
Author-email: cuberiser@gmail.com
License: UNKNOWN
Platform: UNKNOWN
Requires-Python: >=3.10.0
License-File: LICENSE
